[
    {
        "zeit": "19:41",
        "echte_zeit": "19:41",
        "linie": "RE7",
        "ziel": "Lübbenau(Spreewald)",
        "gleis": "2",
        "info": "pünktlich",
        "begruendung": "",
        "update": "19:36"
    },
    {
        "zeit": "20:19",
        "echte_zeit": "20:19",
        "linie": "RE7",
        "ziel": "Dessau Hbf",
        "gleis": "1",
        "info": "pünktlich",
        "begruendung": "",
        "update": "19:36"
    },
    {
        "zeit": "20:41",
        "echte_zeit": "20:41",
        "linie": "RE7",
        "ziel": "Berlin-Charlottenbur",
        "gleis": "2",
        "info": "pünktlich",
        "begruendung": "",
        "update": "19:36"
    }
]