[
    {
        "zeit": "18:19",
        "echte_zeit": "18:50",
        "linie": "RE7",
        "ziel": "Dessau Hbf",
        "gleis": "1",
        "info": "FÄLLT AUS",
        "begruendung": "",
        "update": "18:55"
    },
    {
        "zeit": "18:41",
        "echte_zeit": "18:59",
        "linie": "RE7",
        "ziel": "Senftenberg",
        "gleis": "2",
        "info": "+18",
        "begruendung": "",
        "update": "18:55"
    },
    {
        "zeit": "19:00",
        "echte_zeit": "19:00",
        "linie": "RE7",
        "ziel": "Berlin-Wannsee",
        "gleis": "1",
        "info": "pünktlich",
        "begruendung": "",
        "update": "18:55"
    },
    {
        "zeit": "19:19",
        "echte_zeit": "19:19",
        "linie": "RE7",
        "ziel": "Dessau Hbf",
        "gleis": "1",
        "info": "pünktlich",
        "begruendung": "",
        "update": "18:55"
    },
    {
        "zeit": "19:41",
        "echte_zeit": "19:41",
        "linie": "RE7",
        "ziel": "Lübbenau(Spreewald)",
        "gleis": "1",
        "info": "pünktlich",
        "begruendung": "",
        "update": "18:55"
    }
]