[
    {
        "zeit": "04:06",
        "echte_zeit": "04:06",
        "linie": "S2",
        "ziel": "Leipzig-Connewitz",
        "gleis": "4",
        "info": "pünktlich",
        "begruendung": "",
        "update": "03:12"
    },
    {
        "zeit": "04:49",
        "echte_zeit": "04:49",
        "linie": "RE13",
        "ziel": "Magdeburg Hbf",
        "gleis": "5",
        "info": "pünktlich",
        "begruendung": "",
        "update": "03:12"
    },
    {
        "zeit": "04:54",
        "echte_zeit": "04:54",
        "linie": "RB50",
        "ziel": "Aschersleben",
        "gleis": "7",
        "info": "pünktlich",
        "begruendung": "",
        "update": "03:12"
    }
]