[
    {
        "zeit": "21:05",
        "echte_zeit": "21:19",
        "linie": "IC2448",
        "ziel": "Hannover Hbf",
        "gleis": "2",
        "info": "+14",
        "begruendung": "",
        "update": "21:23"
    },
    {
        "zeit": "21:10",
        "echte_zeit": "21:14",
        "linie": "RB51",
        "ziel": "Falkenberg(Elster)",
        "gleis": "6",
        "info": "+4",
        "begruendung": "",
        "update": "21:23"
    },
    {
        "zeit": "21:11",
        "echte_zeit": "21:18",
        "linie": "S2",
        "ziel": "Leipzig Hbf",
        "gleis": "4",
        "info": "+7",
        "begruendung": "",
        "update": "21:23"
    },
    {
        "zeit": "21:59",
        "echte_zeit": "21:59",
        "linie": "RE13",
        "ziel": "Leipzig Hbf",
        "gleis": "3",
        "info": "pünktlich",
        "begruendung": "",
        "update": "21:23"
    },
    {
        "zeit": "22:05",
        "echte_zeit": "22:05",
        "linie": "RE7",
        "ziel": "Berlin-Charlottenbur",
        "gleis": "4",
        "info": "pünktlich",
        "begruendung": "",
        "update": "21:23"
    },
    {
        "zeit": "22:11",
        "echte_zeit": "22:11",
        "linie": "RB50",
        "ziel": "Aschersleben",
        "gleis": "7",
        "info": "pünktlich",
        "begruendung": "",
        "update": "21:23"
    },
    {
        "zeit": "22:59",
        "echte_zeit": "22:59",
        "linie": "RE13",
        "ziel": "Leipzig Hbf",
        "gleis": "3",
        "info": "pünktlich",
        "begruendung": "",
        "update": "21:23"
    }
]