[
    {
        "zeit": "05:36",
        "echte_zeit": "05:37",
        "linie": "RE2",
        "ziel": "Bad Kleinen",
        "gleis": "1",
        "info": "+1",
        "begruendung": "",
        "update": "05:35"
    },
    {
        "zeit": "06:15",
        "echte_zeit": "06:16",
        "linie": "RE2",
        "ziel": "Lübeck Hbf",
        "gleis": "1",
        "info": "+1",
        "begruendung": "",
        "update": "05:35"
    },
    {
        "zeit": "06:36",
        "echte_zeit": "06:36",
        "linie": "RE2",
        "ziel": "Bad Kleinen",
        "gleis": "1",
        "info": "pünktlich",
        "begruendung": "",
        "update": "05:35"
    }
]