[
    {
        "zeit": "05:36",
        "echte_zeit": "05:49",
        "linie": "RE2",
        "ziel": "Bad Kleinen",
        "gleis": "1",
        "info": "+13",
        "begruendung": "",
        "update": "05:44"
    },
    {
        "zeit": "06:15",
        "echte_zeit": "06:20",
        "linie": "RE2",
        "ziel": "Lübeck Hbf",
        "gleis": "1",
        "info": "+5",
        "begruendung": "",
        "update": "05:44"
    },
    {
        "zeit": "06:36",
        "echte_zeit": "06:46",
        "linie": "RE2",
        "ziel": "Bad Kleinen",
        "gleis": "1",
        "info": "+10",
        "begruendung": "",
        "update": "05:44"
    }
]