[
    {
        "zeit": "05:20",
        "echte_zeit": "05:28",
        "linie": "RE13",
        "ziel": "Magdeburg Hbf",
        "gleis": "2",
        "info": "+8",
        "grund": "",
        "update": "05:19"
    },
    {
        "zeit": "05:27",
        "echte_zeit": "05:38",
        "linie": "RE13",
        "ziel": "Leipzig Hbf",
        "gleis": "1",
        "info": "+11",
        "grund": "",
        "update": "05:19"
    },
    {
        "zeit": "05:32",
        "echte_zeit": "05:32",
        "linie": "Bus712",
        "ziel": "Burg",
        "gleis": "2",
        "info": "",
        "grund": "",
        "update": "05:19"
    },
    {
        "zeit": "05:45",
        "echte_zeit": "05:45",
        "linie": "Bus708",
        "ziel": "Königsborn",
        "gleis": "4",
        "info": "",
        "grund": "",
        "update": "05:19"
    },
    {
        "zeit": "05:55",
        "echte_zeit": "05:55",
        "linie": "Bus702",
        "ziel": "Königsborn",
        "gleis": "1",
        "info": "",
        "grund": "",
        "update": "05:19"
    },
    {
        "zeit": "06:01",
        "echte_zeit": "06:01",
        "linie": "RE14",
        "ziel": "Magdeburg Hbf",
        "gleis": "2",
        "info": "",
        "grund": "",
        "update": "05:19"
    },
    {
        "zeit": "06:05",
        "echte_zeit": "06:05",
        "linie": "Bus705",
        "ziel": "Dornburg",
        "gleis": "4",
        "info": "",
        "grund": "",
        "update": "05:19"
    }
]