[
    {
        "zeit": "03:32",
        "echte_zeit": "03:32",
        "linie": "S4",
        "ziel": "Eilenburg",
        "gleis": "2D",
        "info": "",
        "grund": "",
        "update": "03:28"
    },
    {
        "zeit": "03:33",
        "echte_zeit": "03:33",
        "linie": "S4",
        "ziel": "Wurzen",
        "gleis": "1A",
        "info": "",
        "grund": "",
        "update": "03:28"
    },
    {
        "zeit": "03:33",
        "echte_zeit": "03:33",
        "linie": "STRN10",
        "ziel": "Lößnig über Connew",
        "gleis": "B",
        "info": "",
        "grund": "",
        "update": "03:28"
    },
    {
        "zeit": "03:33",
        "echte_zeit": "03:33",
        "linie": "STRN17",
        "ziel": "Lausen",
        "gleis": "C",
        "info": "",
        "grund": "",
        "update": "03:28"
    },
    {
        "zeit": "03:33",
        "echte_zeit": "03:33",
        "linie": "BusN1",
        "ziel": "Plagwitz - Knautkl",
        "gleis": "C",
        "info": "",
        "grund": "",
        "update": "03:28"
    },
    {
        "zeit": "03:33",
        "echte_zeit": "03:33",
        "linie": "BusN2",
        "ziel": "Lindenau - Markran",
        "gleis": "C",
        "info": "",
        "grund": "",
        "update": "03:28"
    },
    {
        "zeit": "03:33",
        "echte_zeit": "03:33",
        "linie": "BusN3",
        "ziel": "Rückmarsdorf",
        "gleis": "C",
        "info": "",
        "grund": "",
        "update": "03:28"
    },
    {
        "zeit": "03:33",
        "echte_zeit": "03:33",
        "linie": "BusN4",
        "ziel": "Wahren - Schkeudit",
        "gleis": "A",
        "info": "",
        "grund": "",
        "update": "03:28"
    },
    {
        "zeit": "03:33",
        "echte_zeit": "03:33",
        "linie": "BusN5",
        "ziel": "Gohlis - Wiederitz",
        "gleis": "A",
        "info": "",
        "grund": "",
        "update": "03:28"
    },
    {
        "zeit": "03:33",
        "echte_zeit": "03:33",
        "linie": "BusN6",
        "ziel": "Thekla - Taucha",
        "gleis": "B",
        "info": "",
        "grund": "",
        "update": "03:28"
    },
    {
        "zeit": "03:33",
        "echte_zeit": "03:33",
        "linie": "BusN7",
        "ziel": "Baalsdorf - Engels",
        "gleis": "B",
        "info": "",
        "grund": "",
        "update": "03:28"
    },
    {
        "zeit": "03:33",
        "echte_zeit": "03:33",
        "linie": "BusN8",
        "ziel": "Stötteritz - Liebe",
        "gleis": "D",
        "info": "",
        "grund": "",
        "update": "03:28"
    },
    {
        "zeit": "03:33",
        "echte_zeit": "03:33",
        "linie": "BusN9",
        "ziel": "Lößnig - Markkleeb",
        "gleis": "D",
        "info": "",
        "grund": "",
        "update": "03:28"
    },
    {
        "zeit": "03:33",
        "echte_zeit": "03:33",
        "linie": "STRN17",
        "ziel": "Paunsdorf-Nord übe",
        "gleis": "D",
        "info": "",
        "grund": "",
        "update": "03:28"
    },
    {
        "zeit": "03:36",
        "echte_zeit": "03:36",
        "linie": "S3",
        "ziel": "Halle-Nietleben",
        "gleis": "2",
        "info": "",
        "grund": "",
        "update": "03:28"
    },
    {
        "zeit": "03:37",
        "echte_zeit": "03:37",
        "linie": "S3",
        "ziel": "Geithain",
        "gleis": "1B-C",
        "info": "",
        "grund": "",
        "update": "03:28"
    },
    {
        "zeit": "03:37",
        "echte_zeit": "03:37",
        "linie": "S6",
        "ziel": "Markranstädt",
        "gleis": "12",
        "info": "",
        "grund": "",
        "update": "03:28"
    },
    {
        "zeit": "03:38",
        "echte_zeit": "03:38",
        "linie": "STR11",
        "ziel": "Schkeuditz",
        "gleis": "E",
        "info": "",
        "grund": "",
        "update": "03:28"
    },
    {
        "zeit": "03:40",
        "echte_zeit": "03:40",
        "linie": "S2",
        "ziel": "Bitterfeld",
        "gleis": "7",
        "info": "",
        "grund": "",
        "update": "03:28"
    },
    {
        "zeit": "03:41",
        "echte_zeit": "03:41",
        "linie": "S5",
        "ziel": "Leipzig/Halle Flug",
        "gleis": "2",
        "info": "",
        "grund": "",
        "update": "03:28"
    },
    {
        "zeit": "03:46",
        "echte_zeit": "03:46",
        "linie": "S1",
        "ziel": "Leipzig Miltitzer ",
        "gleis": "2",
        "info": "",
        "grund": "",
        "update": "03:28"
    },
    {
        "zeit": "04:08",
        "echte_zeit": "04:08",
        "linie": "STR11",
        "ziel": "Schkeuditz",
        "gleis": "E",
        "info": "",
        "grund": "",
        "update": "03:28"
    },
    {
        "zeit": "04:09",
        "echte_zeit": "04:09",
        "linie": "STR16",
        "ziel": "Messegelände",
        "gleis": "E",
        "info": "",
        "grund": "",
        "update": "03:28"
    },
    {
        "zeit": "04:20",
        "echte_zeit": "04:20",
        "linie": "STR15",
        "ziel": "Meusdorf",
        "gleis": "D",
        "info": "",
        "grund": "",
        "update": "03:28"
    },
    {
        "zeit": "04:23",
        "echte_zeit": "04:23",
        "linie": "STR16",
        "ziel": "Messegelände",
        "gleis": "A",
        "info": "",
        "grund": "",
        "update": "03:28"
    },
    {
        "zeit": "04:24",
        "echte_zeit": "04:24",
        "linie": "STR1",
        "ziel": "Mockau, Post",
        "gleis": "B",
        "info": "",
        "grund": "",
        "update": "03:28"
    },
    {
        "zeit": "04:26",
        "echte_zeit": "04:26",
        "linie": "STR12",
        "ziel": "Gohlis-Nord über Z",
        "gleis": "C",
        "info": "",
        "grund": "",
        "update": "03:28"
    },
    {
        "zeit": "04:26",
        "echte_zeit": "04:26",
        "linie": "STR9",
        "ziel": "Thekla",
        "gleis": "A",
        "info": "",
        "grund": "",
        "update": "03:28"
    },
    {
        "zeit": "04:27",
        "echte_zeit": "04:27",
        "linie": "STR11",
        "ziel": "Wahren",
        "gleis": "E",
        "info": "",
        "grund": "",
        "update": "03:28"
    },
    {
        "zeit": "04:28",
        "echte_zeit": "04:28",
        "linie": "S5",
        "ziel": "Altenburg",
        "gleis": "1",
        "info": "",
        "grund": "",
        "update": "03:28"
    }
]