[
    {
        "zeit": "00:04",
        "echte_zeit": "00:04",
        "linie": "S4",
        "ziel": "Falkenberg(Elster)",
        "gleis": "14",
        "info": "pünktlich",
        "begruendung": "",
        "update": "23:58"
    },
    {
        "zeit": "00:04",
        "echte_zeit": "00:04",
        "linie": "S4",
        "ziel": "Falkenberg(Elster)",
        "gleis": "14",
        "info": "pünktlich",
        "begruendung": "",
        "update": "23:58"
    },
    {
        "zeit": "00:06",
        "echte_zeit": "00:06",
        "linie": "S6",
        "ziel": "Naumburg(Saale)Hbf",
        "gleis": "7",
        "info": "pünktlich",
        "begruendung": "",
        "update": "23:58"
    },
    {
        "zeit": "00:12",
        "echte_zeit": "00:12",
        "linie": "RB113",
        "ziel": "Geithain",
        "gleis": "22",
        "info": "pünktlich",
        "begruendung": "",
        "update": "23:58"
    },
    {
        "zeit": "00:15",
        "echte_zeit": "00:15",
        "linie": "S4",
        "ziel": "Oschatz",
        "gleis": "20",
        "info": "pünktlich",
        "begruendung": "",
        "update": "23:58"
    },
    {
        "zeit": "00:15",
        "echte_zeit": "00:15",
        "linie": "S4",
        "ziel": "Oschatz",
        "gleis": "20",
        "info": "pünktlich",
        "begruendung": "",
        "update": "23:58"
    },
    {
        "zeit": "00:20",
        "echte_zeit": "00:20",
        "linie": "S2",
        "ziel": "Bitterfeld",
        "gleis": "16",
        "info": "pünktlich",
        "begruendung": "",
        "update": "23:58"
    },
    {
        "zeit": "00:27",
        "echte_zeit": "00:27",
        "linie": "S1",
        "ziel": "Leipzig Miltitzer Al",
        "gleis": "8",
        "info": "pünktlich",
        "begruendung": "",
        "update": "23:58"
    },
    {
        "zeit": "00:31",
        "echte_zeit": "00:44",
        "linie": "ICE609",
        "ziel": "Erfurt Hbf",
        "gleis": "11",
        "info": "+13",
        "begruendung": "",
        "update": "23:58"
    },
    {
        "zeit": "00:43",
        "echte_zeit": "00:43",
        "linie": "RB110",
        "ziel": "Grimma ob Bf",
        "gleis": "19",
        "info": "pünktlich",
        "begruendung": "",
        "update": "23:58"
    },
    {
        "zeit": "00:45",
        "echte_zeit": "01:40",
        "linie": "ICE2592",
        "ziel": "Berlin Südkreuz",
        "gleis": "-",
        "info": "+55",
        "begruendung": "",
        "update": "23:58"
    },
    {
        "zeit": "00:48",
        "echte_zeit": "00:48",
        "linie": "S3",
        "ziel": "Geithain",
        "gleis": "-",
        "info": "pünktlich",
        "begruendung": "",
        "update": "23:58"
    },
    {
        "zeit": "01:16",
        "echte_zeit": "01:16",
        "linie": "ICE905",
        "ziel": "München Hbf",
        "gleis": "10",
        "info": "FÄLLT AUS",
        "begruendung": "",
        "update": "23:58"
    },
    {
        "zeit": "23:48",
        "echte_zeit": "23:49",
        "linie": "S3",
        "ziel": "Geithain",
        "gleis": "9",
        "info": "+1",
        "begruendung": "",
        "update": "23:58"
    },
    {
        "zeit": "23:49",
        "echte_zeit": "00:34",
        "linie": "IC60408",
        "ziel": "Zürich HB",
        "gleis": "12",
        "info": "+45",
        "begruendung": "",
        "update": "23:58"
    },
    {
        "zeit": "23:49",
        "echte_zeit": "00:34",
        "linie": "NJ408",
        "ziel": "Zürich HB",
        "gleis": "12",
        "info": "+45",
        "begruendung": "",
        "update": "23:58"
    },
    {
        "zeit": "23:49",
        "echte_zeit": "00:34",
        "linie": "EC458",
        "ziel": "Zürich HB",
        "gleis": "12",
        "info": "+45",
        "begruendung": "",
        "update": "23:58"
    },
    {
        "zeit": "23:49",
        "echte_zeit": "00:34",
        "linie": "EN40458",
        "ziel": "Zürich HB",
        "gleis": "12",
        "info": "+45",
        "begruendung": "",
        "update": "23:58"
    },
    {
        "zeit": "23:51",
        "echte_zeit": "23:50",
        "linie": "S1",
        "ziel": "Leipzig Miltitzer Al",
        "gleis": "8",
        "info": "pünktlich",
        "begruendung": "",
        "update": "23:58"
    }
]