[
    {
        "zeit": "04:11",
        "echte_zeit": "",
        "linie": "STR14",
        "ziel": "S-Bf. Plagwitz",
        "gleis": "G",
        "info": ""
    },
    {
        "zeit": "04:07",
        "echte_zeit": "",
        "linie": "STR1",
        "ziel": "Mockau, Post",
        "gleis": "B",
        "info": ""
    },
    {
        "zeit": "04:14",
        "echte_zeit": "",
        "linie": "STR12",
        "ziel": "Gohlis-Nord über Z",
        "gleis": "C",
        "info": ""
    },
    {
        "zeit": "04:10",
        "echte_zeit": "",
        "linie": "STR14",
        "ziel": "Klinikum St. Georg",
        "gleis": "A",
        "info": ""
    },
    {
        "zeit": "04:12",
        "echte_zeit": "",
        "linie": "S3",
        "ziel": "Halle-Nietleben",
        "gleis": "-",
        "info": ""
    },
    {
        "zeit": "04:12",
        "echte_zeit": "",
        "linie": "STR15",
        "ziel": "Meusdorf",
        "gleis": "D",
        "info": ""
    },
    {
        "zeit": "04:13",
        "echte_zeit": "",
        "linie": "STR16",
        "ziel": "Messegelände",
        "gleis": "E",
        "info": ""
    },
    {
        "zeit": "04:18",
        "echte_zeit": "",
        "linie": "S3",
        "ziel": "Borna(Leipzig)",
        "gleis": "1",
        "info": ""
    },
    {
        "zeit": "04:18",
        "echte_zeit": "",
        "linie": "STR1",
        "ziel": "Mockau, Post",
        "gleis": "B",
        "info": ""
    },
    {
        "zeit": "04:19",
        "echte_zeit": "",
        "linie": "STR9",
        "ziel": "Thekla",
        "gleis": "A",
        "info": ""
    },
    {
        "zeit": "04:22",
        "echte_zeit": "",
        "linie": "STR7",
        "ziel": "Böhlitz-Ehrenberg",
        "gleis": "C",
        "info": ""
    },
    {
        "zeit": "04:22",
        "echte_zeit": "",
        "linie": "STR11",
        "ziel": "Hänichen",
        "gleis": "A",
        "info": ""
    },
    {
        "zeit": "04:23",
        "echte_zeit": "",
        "linie": "STR14",
        "ziel": "S-Bf. Plagwitz",
        "gleis": "G",
        "info": ""
    },
    {
        "zeit": "04:22",
        "echte_zeit": "",
        "linie": "STR16",
        "ziel": "Messegelände",
        "gleis": "A",
        "info": ""
    },
    {
        "zeit": "04:22",
        "echte_zeit": "",
        "linie": "STR10",
        "ziel": "Lößnig über Connew",
        "gleis": "G",
        "info": ""
    },
    {
        "zeit": "04:24",
        "echte_zeit": "",
        "linie": "STR14",
        "ziel": "Klinikum St. Georg",
        "gleis": "A",
        "info": ""
    },
    {
        "zeit": "04:27",
        "echte_zeit": "",
        "linie": "S1",
        "ziel": "Leipzig Miltitzer ",
        "gleis": "2",
        "info": ""
    },
    {
        "zeit": "04:27",
        "echte_zeit": "",
        "linie": "STR15",
        "ziel": "Meusdorf",
        "gleis": "D",
        "info": ""
    },
    {
        "zeit": "04:28",
        "echte_zeit": "",
        "linie": "S5",
        "ziel": "Zwickau(Sachs)Hbf",
        "gleis": "1",
        "info": ""
    },
    {
        "zeit": "04:30",
        "echte_zeit": "",
        "linie": "STR9",
        "ziel": "Thekla",
        "gleis": "E",
        "info": ""
    },
    {
        "zeit": "04:32",
        "echte_zeit": "",
        "linie": "S5",
        "ziel": "Halle-Trotha",
        "gleis": "2",
        "info": ""
    },
    {
        "zeit": "04:34",
        "echte_zeit": "",
        "linie": "S1",
        "ziel": "Leipzig-Stötteritz",
        "gleis": "1",
        "info": ""
    },
    {
        "zeit": "04:33",
        "echte_zeit": "",
        "linie": "STR1",
        "ziel": "Mockau, Post",
        "gleis": "B",
        "info": ""
    },
    {
        "zeit": "04:34",
        "echte_zeit": "",
        "linie": "STR4",
        "ziel": "Gohlis, Landsberge",
        "gleis": "C",
        "info": ""
    },
    {
        "zeit": "04:36",
        "echte_zeit": "",
        "linie": "STR11",
        "ziel": "Schkeuditz",
        "gleis": "A",
        "info": ""
    },
    {
        "zeit": "04:37",
        "echte_zeit": "",
        "linie": "S2",
        "ziel": "Dessau Hbf",
        "gleis": "2",
        "info": ""
    },
    {
        "zeit": "04:37",
        "echte_zeit": "",
        "linie": "STR14",
        "ziel": "S-Bf. Plagwitz",
        "gleis": "G",
        "info": ""
    },
    {
        "zeit": "04:37",
        "echte_zeit": "",
        "linie": "Bus72",
        "ziel": "Paunsdorf, Strbf. ",
        "gleis": "D",
        "info": ""
    },
    {
        "zeit": "04:38",
        "echte_zeit": "",
        "linie": "S2",
        "ziel": "Leipzig-Connewitz",
        "gleis": "1",
        "info": ""
    },
    {
        "zeit": "04:38",
        "echte_zeit": "",
        "linie": "STR12",
        "ziel": "Gohlis-Nord über Z",
        "gleis": "C",
        "info": ""
    },
    {
        "zeit": "04:39",
        "echte_zeit": "",
        "linie": "STR14",
        "ziel": "Klinikum St. Georg",
        "gleis": "A",
        "info": ""
    },
    {
        "zeit": "04:39",
        "echte_zeit": "",
        "linie": "STR4",
        "ziel": "Stötteritz",
        "gleis": "D",
        "info": ""
    },
    {
        "zeit": "04:40",
        "echte_zeit": "",
        "linie": "STR7",
        "ziel": "Böhlitz-Ehrenberg",
        "gleis": "C",
        "info": ""
    },
    {
        "zeit": "04:40",
        "echte_zeit": "",
        "linie": "STR1",
        "ziel": "Lausen",
        "gleis": "A",
        "info": ""
    },
    {
        "zeit": "04:40",
        "echte_zeit": "",
        "linie": "STR11",
        "ziel": "Markkleeberg-Ost",
        "gleis": "B",
        "info": ""
    },
    {
        "zeit": "04:42",
        "echte_zeit": "",
        "linie": "S3",
        "ziel": "Halle-Nietleben",
        "gleis": "2",
        "info": ""
    },
    {
        "zeit": "04:42",
        "echte_zeit": "",
        "linie": "STR15",
        "ziel": "Meusdorf",
        "gleis": "D",
        "info": ""
    },
    {
        "zeit": "04:42",
        "echte_zeit": "",
        "linie": "STR16",
        "ziel": "Lößnig",
        "gleis": "B",
        "info": ""
    },
    {
        "zeit": "04:42",
        "echte_zeit": "",
        "linie": "STR16",
        "ziel": "Messegelände",
        "gleis": "E",
        "info": ""
    },
    {
        "zeit": "04:44",
        "echte_zeit": "",
        "linie": "S4",
        "ziel": "Leipzig-Stötteritz",
        "gleis": "1",
        "info": ""
    },
    {
        "zeit": "04:43",
        "echte_zeit": "",
        "linie": "RB110",
        "ziel": "Döbeln Hbf",
        "gleis": "20",
        "info": ""
    },
    {
        "zeit": "04:43",
        "echte_zeit": "",
        "linie": "STR9",
        "ziel": "S-Bf. Connewitz",
        "gleis": "F",
        "info": ""
    },
    {
        "zeit": "04:44",
        "echte_zeit": "",
        "linie": "STR10",
        "ziel": "Wahren",
        "gleis": "E",
        "info": ""
    },
    {
        "zeit": "04:45",
        "echte_zeit": "",
        "linie": "STR9",
        "ziel": "Thekla",
        "gleis": "E",
        "info": ""
    },
    {
        "zeit": "04:49",
        "echte_zeit": "",
        "linie": "S4",
        "ziel": "Eilenburg",
        "gleis": "2",
        "info": ""
    },
    {
        "zeit": "04:46",
        "echte_zeit": "",
        "linie": "STR15",
        "ziel": "Miltitz",
        "gleis": "C",
        "info": ""
    },
    {
        "zeit": "04:46",
        "echte_zeit": "",
        "linie": "STR16",
        "ziel": "Messegelände",
        "gleis": "A",
        "info": ""
    },
    {
        "zeit": "04:48",
        "echte_zeit": "",
        "linie": "S3",
        "ziel": "Geithain",
        "gleis": "1",
        "info": ""
    },
    {
        "zeit": "04:48",
        "echte_zeit": "",
        "linie": "STR1",
        "ziel": "Mockau, Post",
        "gleis": "B",
        "info": ""
    },
    {
        "zeit": "04:48",
        "echte_zeit": "",
        "linie": "STR3",
        "ziel": "Knautkleeberg",
        "gleis": "C",
        "info": ""
    },
    {
        "zeit": "04:48",
        "echte_zeit": "",
        "linie": "STR7",
        "ziel": "Sommerfeld über To",
        "gleis": "D",
        "info": ""
    },
    {
        "zeit": "04:49",
        "echte_zeit": "",
        "linie": "STR4",
        "ziel": "Gohlis, Landsberge",
        "gleis": "C",
        "info": ""
    },
    {
        "zeit": "04:50",
        "echte_zeit": "",
        "linie": "Bus73",
        "ziel": "Baalsdorf",
        "gleis": "D",
        "info": ""
    },
    {
        "zeit": "04:50",
        "echte_zeit": "",
        "linie": "STR8",
        "ziel": "Grünau-Nord",
        "gleis": "G",
        "info": ""
    },
    {
        "zeit": "04:50",
        "echte_zeit": "",
        "linie": "STR12",
        "ziel": "Johannisplatz",
        "gleis": "D",
        "info": ""
    },
    {
        "zeit": "04:51",
        "echte_zeit": "",
        "linie": "STR14",
        "ziel": "S-Bf. Plagwitz",
        "gleis": "B",
        "info": ""
    },
    {
        "zeit": "04:51",
        "echte_zeit": "",
        "linie": "STR11",
        "ziel": "Hänichen",
        "gleis": "A",
        "info": ""
    },
    {
        "zeit": "04:52",
        "echte_zeit": "",
        "linie": "STR14",
        "ziel": "Klinikum St. Georg",
        "gleis": "A",
        "info": ""
    },
    {
        "zeit": "04:53",
        "echte_zeit": "",
        "linie": "STR11",
        "ziel": "Markkleeberg-Ost",
        "gleis": "B",
        "info": ""
    },
    {
        "zeit": "04:53",
        "echte_zeit": "",
        "linie": "STR12",
        "ziel": "Gohlis-Nord über Z",
        "gleis": "C",
        "info": ""
    },
    {
        "zeit": "04:54",
        "echte_zeit": "",
        "linie": "STR4",
        "ziel": "Stötteritz",
        "gleis": "D",
        "info": ""
    },
    {
        "zeit": "04:55",
        "echte_zeit": "",
        "linie": "STR1",
        "ziel": "Lausen",
        "gleis": "A",
        "info": ""
    },
    {
        "zeit": "04:55",
        "echte_zeit": "",
        "linie": "STR3",
        "ziel": "Taucha",
        "gleis": "B",
        "info": ""
    },
    {
        "zeit": "04:55",
        "echte_zeit": "",
        "linie": "STR7",
        "ziel": "Böhlitz-Ehrenberg",
        "gleis": "C",
        "info": ""
    },
    {
        "zeit": "04:57",
        "echte_zeit": "",
        "linie": "S1",
        "ziel": "Leipzig Miltitzer ",
        "gleis": "2",
        "info": ""
    },
    {
        "zeit": "04:57",
        "echte_zeit": "",
        "linie": "STR15",
        "ziel": "Meusdorf",
        "gleis": "D",
        "info": ""
    },
    {
        "zeit": "04:57",
        "echte_zeit": "",
        "linie": "STR16",
        "ziel": "Lößnig",
        "gleis": "B",
        "info": ""
    },
    {
        "zeit": "04:57",
        "echte_zeit": "",
        "linie": "Bus84",
        "ziel": "BMW-Werk über Mock",
        "gleis": "O",
        "info": ""
    },
    {
        "zeit": "04:58",
        "echte_zeit": "",
        "linie": "S5X",
        "ziel": "Zwickau(Sachs)Hbf",
        "gleis": "1",
        "info": ""
    },
    {
        "zeit": "04:58",
        "echte_zeit": "",
        "linie": "STR10",
        "ziel": "Wahren",
        "gleis": "A",
        "info": ""
    },
    {
        "zeit": "04:58",
        "echte_zeit": "",
        "linie": "STR9",
        "ziel": "S-Bf. Connewitz",
        "gleis": "F",
        "info": ""
    },
    {
        "zeit": "05:00",
        "echte_zeit": "",
        "linie": "RE50",
        "ziel": "Dresden Hbf",
        "gleis": "21",
        "info": ""
    },
    {
        "zeit": "05:00",
        "echte_zeit": "",
        "linie": "Bus72",
        "ziel": "Paunsdorf, Strbf. ",
        "gleis": "D",
        "info": ""
    },
    {
        "zeit": "05:00",
        "echte_zeit": "",
        "linie": "Bus84",
        "ziel": "BMW-Werk über Mess",
        "gleis": "O",
        "info": ""
    },
    {
        "zeit": "05:00",
        "echte_zeit": "",
        "linie": "STR9",
        "ziel": "Thekla",
        "gleis": "E",
        "info": ""
    },
    {
        "zeit": "05:01",
        "echte_zeit": "",
        "linie": "STR15",
        "ziel": "Miltitz",
        "gleis": "C",
        "info": ""
    },
    {
        "zeit": "05:01",
        "echte_zeit": "",
        "linie": "STR16",
        "ziel": "Messegelände",
        "gleis": "A",
        "info": ""
    },
    {
        "zeit": "05:01",
        "echte_zeit": "",
        "linie": "Bus89",
        "ziel": "Connewitzer Kreuz",
        "gleis": "I",
        "info": ""
    },
    {
        "zeit": "05:02",
        "echte_zeit": "",
        "linie": "S5",
        "ziel": "Halle-Trotha",
        "gleis": "2",
        "info": ""
    },
    {
        "zeit": "05:03",
        "echte_zeit": "",
        "linie": "S1",
        "ziel": "Leipzig-Stötteritz",
        "gleis": "1",
        "info": ""
    },
    {
        "zeit": "05:03",
        "echte_zeit": "",
        "linie": "STR1",
        "ziel": "Mockau, Post",
        "gleis": "B",
        "info": ""
    },
    {
        "zeit": "05:03",
        "echte_zeit": "",
        "linie": "STR3",
        "ziel": "Knautkleeberg",
        "gleis": "C",
        "info": ""
    },
    {
        "zeit": "05:03",
        "echte_zeit": "",
        "linie": "STR7",
        "ziel": "Sommerfeld über To",
        "gleis": "D",
        "info": ""
    },
    {
        "zeit": "05:04",
        "echte_zeit": "",
        "linie": "STR4",
        "ziel": "Gohlis, Landsberge",
        "gleis": "C",
        "info": ""
    },
    {
        "zeit": "05:05",
        "echte_zeit": "",
        "linie": "STR11",
        "ziel": "Schkeuditz",
        "gleis": "A",
        "info": ""
    },
    {
        "zeit": "05:05",
        "echte_zeit": "",
        "linie": "STR12",
        "ziel": "Johannisplatz",
        "gleis": "D",
        "info": ""
    },
    {
        "zeit": "05:06",
        "echte_zeit": "",
        "linie": "RE10",
        "ziel": "Frankfurt(Oder)",
        "gleis": "9",
        "info": ""
    },
    {
        "zeit": "05:06",
        "echte_zeit": "",
        "linie": "S6",
        "ziel": "Naumburg(Saale)Hbf",
        "gleis": "7",
        "info": ""
    },
    {
        "zeit": "05:06",
        "echte_zeit": "",
        "linie": "STR14",
        "ziel": "S-Bf. Plagwitz",
        "gleis": "B",
        "info": ""
    },
    {
        "zeit": "05:07",
        "echte_zeit": "",
        "linie": "STR14",
        "ziel": "Klinikum St. Georg",
        "gleis": "A",
        "info": ""
    }
]