[
    {
        "zeit": "04:04",
        "echte_zeit": "05:47",
        "linie": "ICE1541",
        "ziel": "Berlin Südkreuz",
        "gleis": "7",
        "info": "+103",
        "begruendung": "",
        "update": "04:20"
    },
    {
        "zeit": "04:13",
        "echte_zeit": "04:13",
        "linie": "RE30",
        "ziel": "Halle(Saale)Hbf",
        "gleis": "9",
        "info": "pünktlich",
        "begruendung": "",
        "update": "04:20"
    },
    {
        "zeit": "04:17",
        "echte_zeit": "04:17",
        "linie": "S1",
        "ziel": "Schönebeck-Bad Salze",
        "gleis": "3 D-G",
        "info": "pünktlich",
        "begruendung": "",
        "update": "04:20"
    },
    {
        "zeit": "04:17",
        "echte_zeit": "04:17",
        "linie": "RB36",
        "ziel": "Wolfsburg Hbf",
        "gleis": "4 D-G",
        "info": "pünktlich",
        "begruendung": "",
        "update": "04:20"
    },
    {
        "zeit": "04:18",
        "echte_zeit": "04:18",
        "linie": "RE13",
        "ziel": "Dessau Hbf",
        "gleis": "6 D-G",
        "info": "pünktlich",
        "begruendung": "",
        "update": "04:20"
    },
    {
        "zeit": "04:25",
        "echte_zeit": "04:25",
        "linie": "RE11",
        "ziel": "Thale Hbf",
        "gleis": "4 A-C",
        "info": "pünktlich",
        "begruendung": "",
        "update": "04:20"
    },
    {
        "zeit": "04:33",
        "echte_zeit": "04:33",
        "linie": "RB40",
        "ziel": "Braunschweig Hbf",
        "gleis": "8",
        "info": "pünktlich",
        "begruendung": "",
        "update": "04:20"
    },
    {
        "zeit": "04:37",
        "echte_zeit": "04:37",
        "linie": "RE10",
        "ziel": "Klostermansfeld",
        "gleis": "4 D-G",
        "info": "pünktlich",
        "begruendung": "",
        "update": "04:20"
    },
    {
        "zeit": "04:45",
        "echte_zeit": "04:45",
        "linie": "RB40",
        "ziel": "Genthin",
        "gleis": "7",
        "info": "pünktlich",
        "begruendung": "",
        "update": "04:20"
    },
    {
        "zeit": "04:47",
        "echte_zeit": "04:53",
        "linie": "S1",
        "ziel": "Schönebeck-Bad Salze",
        "gleis": "4 D-G",
        "info": "+6",
        "begruendung": "",
        "update": "04:20"
    },
    {
        "zeit": "04:47",
        "echte_zeit": "04:47",
        "linie": "RE20",
        "ziel": "Salzwedel",
        "gleis": "3 A-C",
        "info": "pünktlich",
        "begruendung": "",
        "update": "04:20"
    },
    {
        "zeit": "04:56",
        "echte_zeit": "04:56",
        "linie": "RE1",
        "ziel": "Berlin Zoologischer ",
        "gleis": "8",
        "info": "pünktlich",
        "begruendung": "",
        "update": "04:20"
    },
    {
        "zeit": "04:59",
        "echte_zeit": "04:59",
        "linie": "RE30",
        "ziel": "Halle(Saale)Hbf",
        "gleis": "5 D-G",
        "info": "pünktlich",
        "begruendung": "",
        "update": "04:20"
    },
    {
        "zeit": "05:06",
        "echte_zeit": "05:06",
        "linie": "RE13",
        "ziel": "Leipzig Hbf",
        "gleis": "6 A-C",
        "info": "pünktlich",
        "begruendung": "",
        "update": "04:20"
    },
    {
        "zeit": "05:10",
        "echte_zeit": "05:10",
        "linie": "S1",
        "ziel": "Osterburg",
        "gleis": "3 A-C",
        "info": "pünktlich",
        "begruendung": "",
        "update": "04:20"
    },
    {
        "zeit": "05:17",
        "echte_zeit": "05:17",
        "linie": "S1",
        "ziel": "Schönebeck-Bad Salze",
        "gleis": "4 D-G",
        "info": "pünktlich",
        "begruendung": "",
        "update": "04:20"
    },
    {
        "zeit": "05:26",
        "echte_zeit": "05:26",
        "linie": "RE1",
        "ziel": "Berlin Ostbahnhof",
        "gleis": "1",
        "info": "pünktlich",
        "begruendung": "",
        "update": "04:20"
    },
    {
        "zeit": "05:30",
        "echte_zeit": "05:30",
        "linie": "RB40",
        "ziel": "Braunschweig Hbf",
        "gleis": "8",
        "info": "pünktlich",
        "begruendung": "",
        "update": "04:20"
    },
    {
        "zeit": "05:31",
        "echte_zeit": "05:31",
        "linie": "RB36",
        "ziel": "Wolfsburg Hbf",
        "gleis": "5 D-G",
        "info": "pünktlich",
        "begruendung": "",
        "update": "04:20"
    },
    {
        "zeit": "05:33",
        "echte_zeit": "05:33",
        "linie": "RB40",
        "ziel": "Genthin",
        "gleis": "7",
        "info": "pünktlich",
        "begruendung": "",
        "update": "04:20"
    },
    {
        "zeit": "05:35",
        "echte_zeit": "05:35",
        "linie": "RE30",
        "ziel": "Halle(Saale)Hbf",
        "gleis": "9",
        "info": "pünktlich",
        "begruendung": "",
        "update": "04:20"
    },
    {
        "zeit": "05:41",
        "echte_zeit": "05:41",
        "linie": "RE20",
        "ziel": "Stendal Hbf",
        "gleis": "3 A-C",
        "info": "pünktlich",
        "begruendung": "",
        "update": "04:20"
    },
    {
        "zeit": "05:42",
        "echte_zeit": "05:42",
        "linie": "RE11",
        "ziel": "Thale Hbf",
        "gleis": "4 D-G",
        "info": "pünktlich",
        "begruendung": "",
        "update": "04:20"
    },
    {
        "zeit": "05:47",
        "echte_zeit": "05:47",
        "linie": "S1",
        "ziel": "Schönebeck-Bad Salze",
        "gleis": "3 D-G",
        "info": "pünktlich",
        "begruendung": "",
        "update": "04:20"
    }
]