[
    {
        "zeit": "06:45",
        "echte_zeit": "06:51",
        "linie": "RE13",
        "ziel": "Leipzig Hbf",
        "gleis": "2",
        "info": "+6",
        "begruendung": "",
        "update": "06:35"
    },
    {
        "zeit": "07:16",
        "echte_zeit": "07:16",
        "linie": "RE13",
        "ziel": "Magdeburg Hbf",
        "gleis": "1",
        "info": "pünktlich",
        "begruendung": "",
        "update": "06:35"
    },
    {
        "zeit": "07:45",
        "echte_zeit": "07:45",
        "linie": "RE13",
        "ziel": "Leipzig Hbf",
        "gleis": "2",
        "info": "pünktlich",
        "begruendung": "",
        "update": "06:35"
    }
]