[
    {
        "zeit": "11:59",
        "echte_zeit": "",
        "linie": "L7",
        "ziel": "Liberec",
        "gleis": "3b",
        "info": ""
    },
    {
        "zeit": "11:59",
        "echte_zeit": "",
        "linie": "L7",
        "ziel": "Seifhennersdorf",
        "gleis": "1a",
        "info": ""
    },
    {
        "zeit": "12:04",
        "echte_zeit": "",
        "linie": "RB65",
        "ziel": "Cottbus Hbf",
        "gleis": "3a",
        "info": ""
    },
    {
        "zeit": "12:05",
        "echte_zeit": "",
        "linie": "RB61",
        "ziel": "Dresden Hbf",
        "gleis": "2a",
        "info": ""
    }
]